Metadata-Version: 2.1
Name: unix-os
Version: 0.4
Summary: `os` and `glob` builtin packages always using UNIX file conventions independently of OS
Home-page: https://omfit.io
Author: OMFIT developers
Author-email: meneghini@fusion.gat.com
License: UNKNOWN
Platform: UNKNOWN
Classifier: Programming Language :: Python :: 2
Classifier: Programming Language :: Python :: 3
Classifier: Operating System :: OS Independent
